{"name":"IUNITOFMEASTEXT$T","description":"Unit of Measure Text","guid":"e4bda3f1-a07c-49c0-a68f-3fd8b99defc3","semantics":"Texts","context":"ABAP_CDS","supportsFull":true,"supportsDelta":false,"mode":"Full","transferDataOnDeltaInit":true,"columns":[{"name":"LANGUAGE","description":"Language Key","abapType":"CharacterString","length":1,"isPrimaryKey":true,"isSelected":true,"selectionPermission":"All","outputLength":2},{"name":"UNITOFMEASURE","description":"Units of Measurement of Various Types","abapType":"CharacterString","length":3,"isPrimaryKey":true,"isSelected":true,"selectionPermission":"All","outputLength":3},{"name":"UNITOFMEASURELONGNAME","description":"Text (30 Characters)","abapType":"CharacterString","length":30,"isSelected":true,"selectionPermission":"All","outputLength":30},{"name":"UNITOFMEASURENAME","description":"Text (length 10)","abapType":"CharacterString","length":10,"isSelected":true,"selectionPermission":"All","outputLength":10},{"name":"UNITOFMEASURETECHNICALNAME","description":"External measurement unit","abapType":"CharacterString","length":6,"isSelected":true,"selectionPermission":"All","outputLength":6},{"name":"UNITOFMEASURE_E","description":"External 3-character meas. unit","abapType":"CharacterString","length":3,"isSelected":true,"selectionPermission":"All","outputLength":3},{"name":"UNITOFMEASURECOMMERCIALNAME","description":"External 3-character meas. unit","abapType":"CharacterString","length":3,"isSelected":true,"selectionPermission":"All","outputLength":3}]}
