{
    "nameGenerator": {
        "suffix": ""
    },
    "internalSettings": {
        "nameGenerator": {
            "suffix": ""
        },
        "sapDateConversion": {
            "enabled": false,
            "replacementForInvalidDate": null,
            "replacementForZeroDate": "0001-01-01",
            "replacementForYear9999": "9999-12-31"
        },
        "existingFileAction": "Replace",
        "columnNameKind": "Code"
    },
    "blobType": "BlockBlob",
    "columnNameKind": "Code",
    "folderPath": "",
    "maxBlobSize": 0
}