{
    "functionName": "/SAPDS/RFC_READ_TABLE2",
    "runInBackgroundJob": false,
    "tables": 
    [
        {
            "name": "IFUNCTLLOCATION",
            "description": "Generated Table for View",
            "isView": true,
            "fields": 
            [
                {
                    "name": "MANDT",
                    "description": "Client",
                    "abapType": "CharacterString",
                    "length": 3,
                    "isPrimaryKey": true,
                    "isSelected": true,
                    "checkTable": "T000",
                    "conversionExit": ""
                },
                {
                    "name": "FUNCTIONALLOCATION",
                    "description": "Functional Location",
                    "abapType": "CharacterString",
                    "length": 30,
                    "isPrimaryKey": true,
                    "isSelected": true,
                    "formattedLength": 40,
                    "conversionExit": "TPLNR"
                },
                {
                    "name": "FUNCLOCATIONSTRUCTURE",
                    "description": "Functional Location Structure Indicator",
                    "abapType": "CharacterString",
                    "length": 5,
                    "isSelected": true,
                    "checkTable": "T370S",
                    "conversionExit": ""
                },
                {
                    "name": "FUNCTIONALLOCATIONCATEGORY",
                    "description": "Functional location category",
                    "abapType": "CharacterString",
                    "length": 1,
                    "isSelected": true,
                    "checkTable": "T370F",
                    "conversionExit": ""
                },
                {
                    "name": "SUPERIORFUNCTIONALLOCATION",
                    "description": "Superior functional location",
                    "abapType": "CharacterString",
                    "length": 30,
                    "isSelected": true,
                    "formattedLength": 40,
                    "checkTable": "IFLOT",
                    "conversionExit": "TPLNR"
                },
                {
                    "name": "CREATIONDATE",
                    "description": "Date on which the object was created",
                    "abapType": "Date",
                    "isSelected": true,
                    "conversionExit": ""
                },
                {
                    "name": "CREATEDBYUSER",
                    "description": "Name of User Who Created the Object",
                    "abapType": "CharacterString",
                    "length": 12,
                    "isSelected": true,
                    "conversionExit": ""
                },
                {
                    "name": "LASTCHANGEDATE",
                    "description": "Date on which the object was last changed",
                    "abapType": "Date",
                    "isSelected": true,
                    "conversionExit": ""
                },
                {
                    "name": "LASTCHANGEDBYUSER",
                    "description": "Name of the user who last changed the object",
                    "abapType": "CharacterString",
                    "length": 12,
                    "isSelected": true,
                    "conversionExit": ""
                },
                {
                    "name": "OPERATIONSTARTDATE",
                    "description": "Start-up Date of the Technical Object",
                    "abapType": "Date",
                    "isSelected": true,
                    "conversionExit": ""
                },
                {
                    "name": "AUTHORIZATIONGROUP",
                    "description": "Technical object authorization group",
                    "abapType": "CharacterString",
                    "length": 4,
                    "isSelected": true,
                    "checkTable": "T370B",
                    "conversionExit": ""
                },
                {
                    "name": "CONSTRUCTIONMATERIAL",
                    "description": "Construction type material of the object",
                    "abapType": "CharacterString",
                    "length": 40,
                    "isSelected": true,
                    "checkTable": "MARA",
                    "conversionExit": "MATN1"
                },
                {
                    "name": "MANUFACTURERPARTNMBR",
                    "description": "Manufacturer part number",
                    "abapType": "CharacterString",
                    "length": 30,
                    "isSelected": true,
                    "conversionExit": ""
                },
                {
                    "name": "MAINTENANCEPLANNINGPLANT",
                    "description": "Maintenance Planning Plant",
                    "abapType": "CharacterString",
                    "length": 4,
                    "isSelected": true,
                    "checkTable": "T399I",
                    "conversionExit": ""
                },
                {
                    "name": "MAINTENANCEPLANNERGROUP",
                    "description": "Planner Group for Customer Service and Plant Maintenance",
                    "abapType": "CharacterString",
                    "length": 3,
                    "isSelected": true,
                    "checkTable": "T024I",
                    "conversionExit": ""
                },
                {
                    "name": "WORKCENTERTYPECODE",
                    "description": "Object Type of CIM Resources for Work Center",
                    "abapType": "CharacterString",
                    "length": 2,
                    "isSelected": true,
                    "conversionExit": ""
                },
                {
                    "name": "WORKCENTERINTERNALID",
                    "description": "Object ID of the Work Center",
                    "abapType": "NumericCharacterString",
                    "length": 8,
                    "isSelected": true,
                    "checkTable": "CRID",
                    "conversionExit": ""
                },
                {
                    "name": "CATALOGPROFILE",
                    "description": "Catalog Profile",
                    "abapType": "CharacterString",
                    "length": 9,
                    "isSelected": true,
                    "checkTable": "T352B",
                    "conversionExit": ""
                },
                {
                    "name": "MAINTOBJECTLOCACCTASSGMTNMBR",
                    "description": "Location and account assignment for technical object",
                    "abapType": "CharacterString",
                    "length": 12,
                    "isSelected": true,
                    "checkTable": "ILOA",
                    "conversionExit": ""
                },
                {
                    "name": "MAINTOBJECTINTERNALID",
                    "description": "Object number",
                    "abapType": "CharacterString",
                    "length": 22,
                    "isSelected": true,
                    "checkTable": "ONR00",
                    "conversionExit": ""
                },
                {
                    "name": "TECHNICALOBJECTTYPE",
                    "description": "Type of Technical Object",
                    "abapType": "CharacterString",
                    "length": 10,
                    "isSelected": true,
                    "checkTable": "T370K",
                    "conversionExit": ""
                },
                {
                    "name": "INVENTORYNUMBER",
                    "description": "Inventory number",
                    "abapType": "CharacterString",
                    "length": 25,
                    "isSelected": true,
                    "conversionExit": ""
                },
                {
                    "name": "SIZEORDIMENSIONTEXT",
                    "description": "Size/dimension",
                    "abapType": "CharacterString",
                    "length": 18,
                    "isSelected": true,
                    "conversionExit": ""
                },
                {
                    "name": "GROSSWEIGHT",
                    "description": "Gross weight",
                    "abapType": "PackedNumber",
                    "length": 13,
                    "decimalCount": 3,
                    "isSelected": true,
                    "formattedLength": 17,
                    "conversionExit": "",
                    "referenceTable": "IFLOT",
                    "referenceField": "GEWEI"
                },
                {
                    "name": "GROSSWEIGHTUNIT",
                    "description": "Weight Unit",
                    "abapType": "CharacterString",
                    "length": 3,
                    "isSelected": true,
                    "checkTable": "T006",
                    "conversionExit": "CUNIT"
                },
                {
                    "name": "ACQUISITIONVALUE",
                    "description": "Acquisition Value",
                    "abapType": "PackedNumber",
                    "length": 13,
                    "decimalCount": 2,
                    "isSelected": true,
                    "formattedLength": 17,
                    "conversionExit": "",
                    "referenceTable": "IFLOT",
                    "referenceField": "WAERS"
                },
                {
                    "name": "CURRENCY",
                    "description": "Currency Key",
                    "abapType": "CharacterString",
                    "length": 5,
                    "isSelected": true,
                    "checkTable": "TCURC",
                    "conversionExit": ""
                },
                {
                    "name": "ACQUISITIONDATE",
                    "description": "Acquisition date",
                    "abapType": "Date",
                    "isSelected": true,
                    "conversionExit": ""
                },
                {
                    "name": "ASSETMANUFACTURERNAME",
                    "description": "Manufacturer of Asset",
                    "abapType": "CharacterString",
                    "length": 30,
                    "isSelected": true,
                    "conversionExit": ""
                },
                {
                    "name": "MANUFACTURERCOUNTRY",
                    "description": "Country of manufacture",
                    "abapType": "CharacterString",
                    "length": 3,
                    "isSelected": true,
                    "checkTable": "T005",
                    "conversionExit": ""
                },
                {
                    "name": "CONSTRUCTIONYEAR",
                    "description": "Year of construction",
                    "abapType": "CharacterString",
                    "length": 4,
                    "isSelected": true,
                    "conversionExit": "GJAHR"
                },
                {
                    "name": "CONSTRUCTIONMONTH",
                    "description": "Month of construction",
                    "abapType": "CharacterString",
                    "length": 2,
                    "isSelected": true,
                    "conversionExit": ""
                },
                {
                    "name": "MANUFACTURERPARTTYPENAME",
                    "description": "Manufacturer model number",
                    "abapType": "CharacterString",
                    "length": 20,
                    "isSelected": true,
                    "conversionExit": ""
                },
                {
                    "name": "MANUFACTURERSERIALNUMBER",
                    "description": "Manufacturer serial number",
                    "abapType": "CharacterString",
                    "length": 30,
                    "isSelected": true,
                    "conversionExit": ""
                },
                {
                    "name": "LASTCHANGEDATETIME",
                    "description": "UTC Time Stamp in Short Form (YYYYMMDDhhmmss)",
                    "abapType": "PackedNumber",
                    "length": 15,
                    "isSelected": true,
                    "formattedLength": 19,
                    "conversionExit": ""
                }
            ]
        }
    ]
}