{"name":"IFICOUNTRY$P","description":"Country","guid":"a7121171-51bc-42be-bfba-58d62b530142","semantics":"MasterDataOrAttributes","context":"ABAP_CDS","supportsFull":true,"supportsDelta":false,"mode":"Full","transferDataOnDeltaInit":true,"columns":[{"name":"COUNTRY","description":"Country key","abapType":"CharacterString","length":3,"isPrimaryKey":true,"isSelected":true,"selectionPermission":"All","outputLength":3},{"name":"COUNTRYTHREELETTERISOCODE","description":"ISO country code 3 char","abapType":"CharacterString","length":3,"isSelected":true,"selectionPermission":"All","outputLength":3},{"name":"COUNTRYTHREEDIGITISOCODE","description":"Numerical field length 3","abapType":"NumericCharacterString","length":3,"isSelected":true,"selectionPermission":"All","outputLength":3},{"name":"COUNTRYCURRENCY","description":"Currency Key","abapType":"CharacterString","length":5,"isSelected":true,"selectionPermission":"All","outputLength":5},{"name":"INDEXBASEDCURRENCY","description":"Currency Key","abapType":"CharacterString","length":5,"isSelected":true,"selectionPermission":"All","outputLength":5},{"name":"HARDCURRENCY","description":"Currency Key","abapType":"CharacterString","length":5,"isSelected":true,"selectionPermission":"All","outputLength":5},{"name":"TAXCALCULATIONPROCEDURE","description":"Costing Sheet","abapType":"CharacterString","length":6,"isSelected":true,"selectionPermission":"All","outputLength":6},{"name":"COUNTRYALTERNATIVECODE","description":"Alternative country keys","abapType":"CharacterString","length":3,"isSelected":true,"selectionPermission":"All","outputLength":3}]}
